MANIFEST.in
README
setup.cfg
setup.py
neon/__init__.py
neon/core.py
neon/example.py
neon.egg-info/PKG-INFO
neon.egg-info/SOURCES.txt
neon.egg-info/dependency_links.txt
neon.egg-info/entry_points.txt
neon.egg-info/not-zip-safe
neon.egg-info/top_level.txt