Metadata-Version: 1.0
Name: neon
Version: 0.1.2
Summary: colorful cui utility
Home-page: https://github.com/yoichi-hiromoto/neon
Author: yoichi.hiromoto
Author-email: yoichi.hiromoto@gmail.com
License: Python Software Foundation License
Keywords: neon colorful cui enjoy happy funny
Platform: UNKNOWN
Classifier: Development Status :: 1 - Planning
Classifier: License :: OSI Approved :: Python Software Foundation License
Classifier: Programming Language :: Python
Classifier: Topic :: Software Development
